diycontroller/__init__.py
diycontroller/__main__.py
diycontroller/accelerometer.hex
diycontroller/main.py
diycontroller/microbit.py
diycontroller/pico.py
diycontroller/receiver.py
diycontroller-0.1.0.dist-info/METADATA
diycontroller-0.1.0.dist-info/WHEEL
diycontroller-0.1.0.dist-info/RECORD
