Metadata-Version: 2.3
Name: diycontroller
Version: 0.1.0
Summary: A project to use the microbit's accelerometer to control your mouse cursor, using a pico as a relay since micro:bit don't work very well with mac and etc.
License: MIT
Author: Oce4nM4n
Author-email: ayushmansihag@gmail.com
Requires-Python: >=3.13
Classifier: License :: OSI Approved :: MIT License
Classifier: Programming Language :: Python :: 3
Classifier: Programming Language :: Python :: 3.13
Requires-Dist: pyautogui (>=0.9.54,<0.10.0)
